hkis/__init__.py
hkis/admin.py
hkis/api.py
hkis/apps.py
hkis/consumers.py
hkis/context_processors.py
hkis/forms.py
hkis/models.py
hkis/routing.py
hkis/serializers.py
hkis/tasks.py
hkis/tests.py
hkis/translation.py
hkis/urls.py
hkis/utils.py
hkis/views.py
hkis/fixtures/initial.json
hkis/locale/fr/LC_MESSAGES/django.po
hkis/locale/fr/LC_MESSAGES/djangojs.po
hkis/migrations/0001_initial.py
hkis/migrations/0002_delete_snippet.py
hkis/migrations/__init__.py
hkis/static/favicon.png
hkis/static/css/bootstrap.min.css
hkis/static/css/codehilite.css
hkis/static/css/grayscale.css
hkis/static/css/hkis.css
hkis/static/css/hkisadmin.css
hkis/static/img/downloads-bg.jpg
hkis/static/img/intro-bg.jpg
hkis/static/img/liberapay.svg
hkis/static/img/loading_anim.gif
hkis/static/img/logo_hackinscience-240x180.png
hkis/static/img/logo_hackinscience.png
hkis/static/img/map-marker.svg
hkis/static/js/bootstrap.min.js
hkis/static/js/exercise.js
hkis/static/js/jquery-slim.min.js
hkis/static/js/profile.js
hkis/templates/hkis/base.html
hkis/templates/hkis/exercise.html
hkis/templates/hkis/index.html
hkis/templates/hkis/layout.html
hkis/templates/hkis/leaderboard.html
hkis/templates/hkis/page.html
hkis/templates/hkis/profile_update.html
hkis/templates/hkis/solutions.html
hkis/templates/hkis/stats_detail.html
hkis/templates/hkis/team.html
hkis/templates/hkis/teams.html
hkis/templates/registration/login.html
hkis/templates/registration/password_change_form.html
hkis/templates/registration/password_reset_confirm.html
hkis/templates/registration/password_reset_form.html
hkis/templates/registration/registration_base.html
hkis/templates/registration/registration_form.html
hkis/templatetags/__init__.py
hkis/templatetags/hkis_extra.py
moulinette/__init__.py
django_hkis-1.0.dist-info/LICENSE
django_hkis-1.0.dist-info/METADATA
django_hkis-1.0.dist-info/WHEEL
django_hkis-1.0.dist-info/top_level.txt
django_hkis-1.0.dist-info/RECORD
