Metadata-Version: 2.1
Name: django-hkis
Version: 1.0
Summary: Django HackInScience exercises app.
Home-page: https://framagit.org/hackinscience/hkis-website
Author: Julien Palard
Author-email: julien@palard.fr
License: MIT License
Platform: UNKNOWN
Classifier: Development Status :: 5 - Production/Stable
Classifier: License :: OSI Approved :: MIT License
Classifier: Programming Language :: Python :: 3
Requires-Python: >=3.7
License-File: LICENSE
Requires-Dist: bleach
Requires-Dist: celery[redis]
Requires-Dist: channels
Requires-Dist: channels-redis
Requires-Dist: django
Requires-Dist: django-ace
Requires-Dist: django-crispy-forms
Requires-Dist: django-extensions
Requires-Dist: django-filter
Requires-Dist: django-modeltranslation
Requires-Dist: django-rest-framework
Requires-Dist: markdown
Requires-Dist: pygments
